do_username/__init__.py
do_username/__main__.py
do_username/generate.py
do_username-1.0.2.dist-info/METADATA
do_username-1.0.2.dist-info/WHEEL
do_username-1.0.2.dist-info/entry_points.txt
do_username-1.0.2.dist-info/top_level.txt
do_username-1.0.2.dist-info/RECORD
