Metadata-Version: 2.1
Name: do-username
Version: 1.0.2
Summary: A Digital Ocean Community themed username generator
Home-page: https://github.com/shreyas44/do_username_py
Author: Shreyas
Author-email: shreyas.sreenivasa@gmail.com
License: MIT
Platform: UNKNOWN
Classifier: Programming Language :: Python :: 3
Classifier: License :: OSI Approved :: MIT License
Classifier: Operating System :: OS Independent
Requires-Python: >=3.6
